lib_b-1.0.3.data/scripts/main.py
libb/__init__.py
libb/dtype.py
libb/exception.py
libb/factorization.py
libb/main.py
libb/utils.py
lib_b-1.0.3.dist-info/LICENSE
lib_b-1.0.3.dist-info/METADATA
lib_b-1.0.3.dist-info/WHEEL
lib_b-1.0.3.dist-info/entry_points.txt
lib_b-1.0.3.dist-info/top_level.txt
lib_b-1.0.3.dist-info/RECORD
