Metadata-Version: 2.1
Name: lib-b
Version: 1.0.3
Summary: A library contains implements of factorization supporting multiple methods and data types
Home-page: https://github.com/Lqlsoftware/lib-b
Author: Robin Lu
Author-email: robin@lqlsoftware.cn
License: UNKNOWN
Platform: UNKNOWN
Classifier: Programming Language :: Python :: 3
Classifier: License :: OSI Approved :: GNU General Public License v3 (GPLv3)
Classifier: Operating System :: OS Independent
Requires-Python: >=3.4.0
